{
  "generatedAt": "2026-02-03T00:00:00Z",
  "description": "Meta JSON mapping UI forms to API endpoints and field constraints that may require Java entity changes.",
  "forms": [
    {
      "id": "/api/employees",
      "httpMethod": "POST",
      "uiComponent": "src/components/EmployeeForm.jsx",
      "purpose": "Create Employee",
      "fields": [
        {
          "name": "firstName",
          "uiType": "textField",
          "required": true,
          "maxLength": 500,
          "javaType": "String",
          "javaAnnotations": ["@Column(length = 100)", "@Size(max = 100)"]
        },
        {
          "name": "lastName",
          "uiType": "textField",
          "required": true,
          "maxLength": 150,
          "javaType": "String",
          "javaAnnotations": ["@Column(length = 150)", "@Size(max = 150)"]
        },
        {
          "name": "email",
          "uiType": "emailField",
          "required": true,
          "maxLength": 254,
          "javaType": "String",
          "javaAnnotations": ["@Column(length = 254)", "@Email"]
        },
        {
          "name": "position",
          "uiType": "textField",
          "required": false,
          "maxLength": 200,
          "javaType": "String",
          "javaAnnotations": ["@Column(length = 200)", "@Size(max = 200)"]
        },
        {
          "name": "salary",
          "uiType": "numberField",
          "required": false,
          "javaType": "BigDecimal",
          "javaAnnotations": ["@Column(precision = 12, scale = 2)"]
        },
        {
          "name": "hiredDate",
          "uiType": "datePicker",
          "required": false,
          "javaType": "LocalDate",
          "javaAnnotations": []
        }
      ],
      "notes": "Front-end enforces max lengths for firstName (500), lastName (150), position (200). Backend Java entity should align column lengths and validation annotations to avoid truncation or persistence errors."
    },
    {
      "id": "/api/employees/{id}",
      "httpMethod": "PUT",
      "uiComponent": "src/components/EmployeeForm.jsx",
      "purpose": "Update Employee",
      "fields": [
        {
          "name": "firstName",
          "uiType": "textField",
          "required": true,
          "maxLength": 500,
          "javaType": "String",
          "javaAnnotations": ["@Column(length = 100)", "@Size(max = 100)"]
        },
        {
          "name": "lastName",
          "uiType": "textField",
          "required": true,
          "maxLength": 150,
          "javaType": "String",
          "javaAnnotations": ["@Column(length = 150)", "@Size(max = 150)"]
        },
        {
          "name": "email",
          "uiType": "emailField",
          "required": true,
          "maxLength": 254,
          "javaType": "String",
          "javaAnnotations": ["@Column(length = 254)", "@Email"]
        },
        {
          "name": "position",
          "uiType": "textField",
          "required": false,
          "maxLength": 200,
          "javaType": "String",
          "javaAnnotations": ["@Column(length = 200)", "@Size(max = 200)"]
        },
        {
          "name": "salary",
          "uiType": "numberField",
          "required": false,
          "javaType": "BigDecimal",
          "javaAnnotations": ["@Column(precision = 12, scale = 2)"]
        },
        {
          "name": "hiredDate",
          "uiType": "datePicker",
          "required": false,
          "javaType": "LocalDate",
          "javaAnnotations": []
        }
      ],
      "notes": "Update uses PUT to `/api/employees/{id}`. Ensure entity constraints match create path. For `id` path parameter, the Java controller mapping should accept a Long/UUID as appropriate."
    }
  ]
}
